apk/__init__.py
apk/main.py
apk/calibration/__init__.py
apk/calibration/main.py
apk/calibration/camera/__init__.py
apk/calibration/camera/calibrator.py
apk/calibration/camera/main.py
apk/calibration/read_sensing/__init__.py
apk/calibration/read_sensing/common.py
apk/calibration/read_sensing/main.py
apk/calibration/read_sensing/parse_result.py
apk/calibration/read_sensing/sensing_reader.py
apk/calibration/read_sensing/utils.py
apk/capture/__init__.py
apk/capture/main.py
apk/capture/camera/__init__.py
apk/capture/camera/capture.py
apk/capture/camera/main.py
apk/capture/lidar/__init__.py
apk/capture/lidar/capture.py
apk/capture/lidar/main.py
apk/format/__init__.py
apk/format/main.py
apk/format/bin2pcd/__init__.py
apk/format/bin2pcd/bin2pcd.py
apk/format/bin2pcd/main.py
apk/format/pcd2bin/__init__.py
apk/format/pcd2bin/main.py
apk/format/pcd2bin/pcd2bin.py
apk/merge/__init__.py
apk/merge/main.py
apk/merge/merge_bag.py
apk/merge/merge_record.py
apk-0.0.6.dist-info/LICENSE
apk-0.0.6.dist-info/METADATA
apk-0.0.6.dist-info/WHEEL
apk-0.0.6.dist-info/entry_points.txt
apk-0.0.6.dist-info/top_level.txt
apk-0.0.6.dist-info/RECORD
