Metadata-Version: 2.1
Name: apk
Version: 0.0.6
Summary: awesome perception kit
Home-page: 
Author: windzu
Author-email: windzu1@gmail.com
License: MIT license
Keywords: adas deeplearning
Classifier: Development Status :: 3 - Alpha
Classifier: Intended Audience :: Developers
Classifier: License :: OSI Approved :: MIT License
Classifier: Natural Language :: English
Classifier: Programming Language :: Python :: 3
Classifier: Programming Language :: Python :: 3.6
Classifier: Programming Language :: Python :: 3.7
Classifier: Programming Language :: Python :: 3.8
Requires-Python: >=3.6
License-File: LICENSE
Requires-Dist: PyGObject
Requires-Dist: rich
Requires-Dist: numpy
Requires-Dist: pycryptodomex
Requires-Dist: rospkg
Requires-Dist: wind-pypcd
Requires-Dist: opencv-python
Requires-Dist: pyyaml
Requires-Dist: gnupg
